cap_client/__init__.py
cap_client/errors.py
cap_client/utils.py
cap_client/version.py
cap_client/api/__init__.py
cap_client/api/analysis_api.py
cap_client/api/base.py
cap_client/api/files_api.py
cap_client/api/metadata_api.py
cap_client/api/permissions_api.py
cap_client/api/repositories_api.py
cap_client/cli/__init__.py
cap_client/cli/analysis_cli.py
cap_client/cli/cli.py
cap_client/cli/files_cli.py
cap_client/cli/metadata_cli.py
cap_client/cli/permissions_cli.py
cap_client/cli/repositories_cli.py
cap_client-1.2.0.dist-info/AUTHORS.rst
cap_client-1.2.0.dist-info/COPYING
cap_client-1.2.0.dist-info/LICENSE
cap_client-1.2.0.dist-info/METADATA
cap_client-1.2.0.dist-info/WHEEL
cap_client-1.2.0.dist-info/entry_points.txt
cap_client-1.2.0.dist-info/top_level.txt
cap_client-1.2.0.dist-info/RECORD
