Metadata-Version: 2.1
Name: cap-client
Version: 1.2.0
Summary: CAP client
Home-page: https://github.com/cernanalysispreservation/cap-client
Author: CAP
Author-email: info@cap.io
License: UNKNOWN
Platform: UNKNOWN
Classifier: Environment :: Web Environment
Classifier: Intended Audience :: Developers
Classifier: License :: OSI Approved :: GNU General Public License v2 (GPLv2)
Classifier: Operating System :: OS Independent
Classifier: Programming Language :: Python
Classifier: Topic :: Internet :: WWW/HTTP :: Dynamic Content
Classifier: Topic :: Software Development :: Libraries :: Python Modules
Classifier: Development Status :: 3 - Alpha
License-File: LICENSE
License-File: COPYING
License-File: AUTHORS.rst
Requires-Dist: click (>=6.7)
Requires-Dist: click-help-colors (>=0.8)
Requires-Dist: requests (>=2.18.4)
Requires-Dist: colorama (>=0.4.3)
Requires-Dist: future (>=0.16.0)
Provides-Extra: all
Requires-Dist: Sphinx (>=1.4.4) ; extra == 'all'
Requires-Dist: sphinx-rtd-theme (>=0.1.9) ; extra == 'all'
Requires-Dist: check-manifest (>=0.25) ; extra == 'all'
Requires-Dist: coverage (>=4.0) ; extra == 'all'
Requires-Dist: mock (>=2.0.0) ; extra == 'all'
Requires-Dist: pydocstyle (>=1.0.0) ; extra == 'all'
Requires-Dist: pytest-cache (>=1.0) ; extra == 'all'
Requires-Dist: pytest-cov (>=1.8.0) ; extra == 'all'
Requires-Dist: flake8 ; extra == 'all'
Requires-Dist: pytest (>=2.8.0) ; extra == 'all'
Requires-Dist: responses (>=0.10.6) ; extra == 'all'
Requires-Dist: pytest-vcr ; extra == 'all'
Provides-Extra: docs
Requires-Dist: Sphinx (>=1.4.4) ; extra == 'docs'
Requires-Dist: sphinx-rtd-theme (>=0.1.9) ; extra == 'docs'
Provides-Extra: tests
Requires-Dist: check-manifest (>=0.25) ; extra == 'tests'
Requires-Dist: coverage (>=4.0) ; extra == 'tests'
Requires-Dist: mock (>=2.0.0) ; extra == 'tests'
Requires-Dist: pydocstyle (>=1.0.0) ; extra == 'tests'
Requires-Dist: pytest-cache (>=1.0) ; extra == 'tests'
Requires-Dist: pytest-cov (>=1.8.0) ; extra == 'tests'
Requires-Dist: flake8 ; extra == 'tests'
Requires-Dist: pytest (>=2.8.0) ; extra == 'tests'
Requires-Dist: responses (>=0.10.6) ; extra == 'tests'
Requires-Dist: pytest-vcr ; extra == 'tests'
